taccsite_cms/__init__.py
taccsite_cms/contrib/__init__.py
taccsite_cms/contrib/_docs/how-to-extend-django-cms-plugin.md
taccsite_cms/contrib/_docs/how-to-override-validation-error-from-parent-model.md
taccsite_cms/contrib/bootstrap4_djangocms_link/cms_plugins.py
taccsite_cms/contrib/bootstrap4_djangocms_picture/cms_plugins.py
taccsite_cms/contrib/constants.py
taccsite_cms/contrib/helpers.py
taccsite_cms/contrib/taccsite_blockquote/__init__.py
taccsite_cms/contrib/taccsite_blockquote/cms_plugins.py
taccsite_cms/contrib/taccsite_blockquote/migrations/0001_initial.py
taccsite_cms/contrib/taccsite_blockquote/migrations/__init__.py
taccsite_cms/contrib/taccsite_blockquote/models.py
taccsite_cms/contrib/taccsite_blockquote/templates/blockquote.html
taccsite_cms/contrib/taccsite_callout/__init__.py
taccsite_cms/contrib/taccsite_callout/cms_plugins.py
taccsite_cms/contrib/taccsite_callout/migrations/0001_initial.py
taccsite_cms/contrib/taccsite_callout/migrations/0002_auto_20210928_1717.py
taccsite_cms/contrib/taccsite_callout/migrations/0003_remove_taccsitecallout_resize_figure_to_fit.py
taccsite_cms/contrib/taccsite_callout/migrations/__init__.py
taccsite_cms/contrib/taccsite_callout/models.py
taccsite_cms/contrib/taccsite_callout/templates/callout.html
taccsite_cms/contrib/taccsite_data_list/__init__.py
taccsite_cms/contrib/taccsite_data_list/cms_plugins.py
taccsite_cms/contrib/taccsite_data_list/constants.py
taccsite_cms/contrib/taccsite_data_list/migrations/0001_initial.py
taccsite_cms/contrib/taccsite_data_list/migrations/0002_auto_20210824_0803.py
taccsite_cms/contrib/taccsite_data_list/migrations/__init__.py
taccsite_cms/contrib/taccsite_data_list/models.py
taccsite_cms/contrib/taccsite_data_list/templates/data_list.html
taccsite_cms/contrib/taccsite_data_list/templates/data_list_item.html
taccsite_cms/contrib/taccsite_data_list/templates/data_list_item_key.html
taccsite_cms/contrib/taccsite_offset/__init__.py
taccsite_cms/contrib/taccsite_offset/cms_plugins.py
taccsite_cms-3.6.0a0.dist-info/WHEEL
taccsite_cms-3.6.0a0.dist-info/METADATA
taccsite_cms-3.6.0a0.dist-info/RECORD
