Metadata-Version: 2.1
Name: taccsite-cms
Version: 3.6.0a0
Summary: DjangoCMS backend for the TACC ACI-WMA Core-CMS Codebase.
Author: TACC-WMA
Author-email: wma-portals@tacc.utexas.edu
Requires-Python: >=3.7,<4.0
Classifier: Programming Language :: Python :: 3
Classifier: Programming Language :: Python :: 3.7
Classifier: Programming Language :: Python :: 3.8
Classifier: Programming Language :: Python :: 3.9
Requires-Dist: Django (==2.2.27)
Requires-Dist: Pillow (==9.0.1)
Requires-Dist: URLObject (==2.4.3)
Requires-Dist: Unidecode (==1.1.1)
Requires-Dist: YURL (==1.0.0)
Requires-Dist: aldryn-apphooks-config (==0.6.0)
Requires-Dist: aldryn-boilerplates (==0.8.0)
Requires-Dist: aldryn-common (==1.0.5)
Requires-Dist: aldryn-search (==1.1.0)
Requires-Dist: asgiref (==3.2.10)
Requires-Dist: astroid (==2.4.2)
Requires-Dist: autopep8 (==1.5.4)
Requires-Dist: certifi (==2020.6.20)
Requires-Dist: chardet (==3.0.4)
Requires-Dist: colorclass (==2.2.0)
Requires-Dist: django-appconf (==1.0.4)
Requires-Dist: django-appdata (==0.3.0)
Requires-Dist: django-auth-ldap (==2.2.0)
Requires-Dist: django-classy-tags (==2.0.0)
Requires-Dist: django-cms (==3.7.4)
Requires-Dist: django-filer (==2.0.2)
Requires-Dist: django-formtools (==2.2)
Requires-Dist: django-haystack (==3.0)
Requires-Dist: django-ipware (==3.0.1)
Requires-Dist: django-js-asset (==1.2.2)
Requires-Dist: django-meta (==1.7.0)
Requires-Dist: django-mptt (==0.11.0)
Requires-Dist: django-parler (==2.2)
Requires-Dist: django-polymorphic (==3.0.0)
Requires-Dist: django-sekizai (==2.0.0)
Requires-Dist: django-settings-export (==1.2.1)
Requires-Dist: django-sortedm2m (==3.0.2)
Requires-Dist: django-spurl (==0.6.7)
Requires-Dist: django-standard-form (==1.1.1)
Requires-Dist: django-taggit (==1.2.0)
Requires-Dist: django-taggit-autosuggest (==0.3.8)
Requires-Dist: django-taggit-templatetags (==0.2.5)
Requires-Dist: django-templatetag-sugar (==1.0)
Requires-Dist: django-test-without-migrations (==0.6)
Requires-Dist: django-treebeard (==4.3.1)
Requires-Dist: djangocms-admin-style (==2.0.0)
Requires-Dist: djangocms-apphook-setup (==0.4.1)
Requires-Dist: djangocms-attributes-field (==2.0.0)
Requires-Dist: djangocms-blog (==1.1.1)
Requires-Dist: djangocms-bootstrap4 (==2.0.0)
Requires-Dist: djangocms-column (==1.11.0)
Requires-Dist: djangocms-file (==3.0.0)
Requires-Dist: djangocms-forms (==0.2.5)
Requires-Dist: djangocms-googlemap (==2.0.0)
Requires-Dist: djangocms-icon (==2.0.0)
Requires-Dist: djangocms-link (==3.0.0)
Requires-Dist: djangocms-page-meta (==0.10.0)
Requires-Dist: djangocms-picture (==3.0.0)
Requires-Dist: djangocms-snippet (==3.0.0)
Requires-Dist: djangocms-style (==3.0.0)
Requires-Dist: djangocms-text-ckeditor (==3.10.0)
Requires-Dist: djangocms-transfer (==1.0.0)
Requires-Dist: djangocms-video (==3.0.0)
Requires-Dist: docopt (==0.6.2)
Requires-Dist: easy-thumbnails (==2.7)
Requires-Dist: elasticsearch (==7.9.1)
Requires-Dist: elasticsearch-dsl (==7.3.0)
Requires-Dist: flake8 (==3.8.3)
Requires-Dist: gunicorn (==20.0.4)
Requires-Dist: hashids (==1.3.1)
Requires-Dist: html5lib (==1.1)
Requires-Dist: idna (==2.10)
Requires-Dist: importlib-metadata (==1.7.0)
Requires-Dist: isort (==5.5.2)
Requires-Dist: jedi (==0.17.2)
Requires-Dist: jsonfield (==3.1.0)
Requires-Dist: lazy-object-proxy (==1.4.3)
Requires-Dist: lxml (==4.6.5)
Requires-Dist: mccabe (==0.6.1)
Requires-Dist: packaging (==20.4)
Requires-Dist: parso (==0.7.1)
Requires-Dist: pip-upgrader (==1.4.15)
Requires-Dist: pluggy (==0.13.1)
Requires-Dist: psycopg2 (==2.8.6)
Requires-Dist: psycopg2-binary (==2.8.6)
Requires-Dist: pyasn1 (==0.4.8)
Requires-Dist: pyasn1-modules (==0.2.8)
Requires-Dist: pycodestyle (==2.6.0)
Requires-Dist: pydocstyle (==5.1.1)
Requires-Dist: pyflakes (==2.2.0)
Requires-Dist: pylint (==2.6.0)
Requires-Dist: pyparsing (==2.4.7)
Requires-Dist: python-dateutil (==2.8.1)
Requires-Dist: python-jsonrpc-server (==0.4.0)
Requires-Dist: python-language-server (==0.35.0)
Requires-Dist: python-ldap (==3.4.0)
Requires-Dist: pytz (==2020.1)
Requires-Dist: requests (==2.27.1)
Requires-Dist: rope (==0.17.0)
Requires-Dist: six (==1.15.0)
Requires-Dist: snowballstemmer (==2.0.0)
Requires-Dist: sqlparse (==0.3.1)
Requires-Dist: tablib (==2.0.0)
Requires-Dist: terminaltables (==3.1.0)
Requires-Dist: toml (==0.10.1)
Requires-Dist: typed-ast (==1.4.1)
Requires-Dist: uWSGI (==2.0.19.1)
Requires-Dist: ujson (==3.2.0)
Requires-Dist: urllib3 (==1.26.5)
Requires-Dist: webencodings (==0.5.1)
Requires-Dist: wrapt (==1.12.1)
Requires-Dist: yapf (==0.30.0)
Requires-Dist: zipp (==3.1.0)
